defi_services/__init__.py
defi_services/abis/__init__.py
defi_services/abis/multicall_v3_abi.py
defi_services/abis/dex/__init__.py
defi_services/abis/dex/biswap/__init__.py
defi_services/abis/dex/biswap/biswap_masterchef_abi.py
defi_services/abis/dex/pancakeswap/__init__.py
defi_services/abis/dex/pancakeswap/factory_v3_abi.py
defi_services/abis/dex/pancakeswap/masterchef_v0_abi.py
defi_services/abis/dex/pancakeswap/masterchef_v3_abi.py
defi_services/abis/dex/pancakeswap/nft_token_abi.py
defi_services/abis/dex/pancakeswap/pancakeswap_lp_token_abi.py
defi_services/abis/dex/pancakeswap/pancakeswap_masterchef_v2_abi.py
defi_services/abis/dex/pancakeswap/pancakeswap_router_v2_abi.py
defi_services/abis/dex/pancakeswap/pancakeswap_v2_factory_abi.py
defi_services/abis/dex/pancakeswap/v3_pool_abi.py
defi_services/abis/dex/quickswap/__init__.py
defi_services/abis/dex/quickswap/factory_v3_abi.py
defi_services/abis/dex/quickswap/nft_token_manager.py
defi_services/abis/dex/quickswap/pool_v3_abi.py
defi_services/abis/dex/spookyswap/__init__.py
defi_services/abis/dex/spookyswap/masterchef_v2_abi.py
defi_services/abis/dex/spookyswap/masterchef_v3_abi.py
defi_services/abis/dex/sushiswap/__init__.py
defi_services/abis/dex/sushiswap/factory_v3_abi.py
defi_services/abis/dex/sushiswap/masterchef_abi.py
defi_services/abis/dex/sushiswap/masterchef_v2_abi.py
defi_services/abis/dex/sushiswap/minichef_abi.py
defi_services/abis/dex/uniswap/__init__.py
defi_services/abis/dex/uniswap/factory_v2_abi.py
defi_services/abis/dex/uniswap/factory_v3_abi.py
defi_services/abis/dex/uniswap/nft_token_manager_abi.py
defi_services/abis/dex/uniswap/pool_v3_abi.py
defi_services/abis/lending/__init__.py
defi_services/abis/lending/aave/__init__.py
defi_services/abis/lending/aave/all_aave_abi.py
defi_services/abis/lending/aave/aave_v2/__init__.py
defi_services/abis/lending/aave/aave_v2/aave_incentives_controller.py
defi_services/abis/lending/aave/aave_v2/aave_oracle.py
defi_state_querier-0.5.35.dist-info/licenses/LICENSE
defi_state_querier-0.5.35.dist-info/METADATA
defi_state_querier-0.5.35.dist-info/WHEEL
defi_state_querier-0.5.35.dist-info/top_level.txt
defi_state_querier-0.5.35.dist-info/RECORD
