Metadata-Version: 2.4
Name: defi-state-querier
Version: 0.5.35
Summary: Calculate apy, apr, and wallet information,... in decentralized applications.
Home-page: https://github.com/Centic-io/defi-state-querier
Author: Viet-Bang Pham
Author-email: phamvietbang2965@gmail.com
Project-URL: Bug Tracker, https://github.com/Centic-io/defi-state-querier
Classifier: Programming Language :: Python :: 3
Classifier: License :: OSI Approved :: MIT License
Classifier: Operating System :: OS Independent
Requires-Python: >=3.6
License-File: LICENSE
Requires-Dist: web3>=6.0.0
Requires-Dist: query-blockchain-state-lib>=1.0.1
Requires-Dist: python-dotenv>=1.0.0
Requires-Dist: pymongo>=4.3.3
Requires-Dist: cosmpy>=0.9.2
Dynamic: author
Dynamic: author-email
Dynamic: classifier
Dynamic: description
Dynamic: description-content-type
Dynamic: home-page
Dynamic: license-file
Dynamic: project-url
Dynamic: requires-dist
Dynamic: requires-python
Dynamic: summary
